<?xml version="1.0" encoding="UTF-8"?>
<Defs>

	<ThingDef Name="OuterRimBuildingBase" ParentName="BuildingBase" Abstract="True">
		<designationCategory>OuterRim_ArchitectHypertech</designationCategory>
		<thingClass>Building</thingClass>
	</ThingDef>

	<ThingDef Name="OuterRimBenchBase" ParentName="OuterRimBuildingBase" Abstract="True">
		<canOverlapZones>false</canOverlapZones>
		<minifiedDef>MinifiedThing</minifiedDef>
		<terrainAffordanceNeeded>Medium</terrainAffordanceNeeded>
		<thingCategories>
			<li>BuildingsProduction</li>
		</thingCategories>
		<statBases>
			<Mass>20</Mass>
		</statBases>
		<interactionCellIcon>DiningChair</interactionCellIcon>
		<comps>
			<li>
				<compClass>CompReportWorkSpeed</compClass>
			</li>
		</comps>
		<placeWorkers>
			<li>PlaceWorker_ReportWorkSpeedPenalties</li>
		</placeWorkers>
		<building>
			<buildingTags>
				<li>Production</li>
			</buildingTags>
		</building>
	</ThingDef>

</Defs>